pythonbook/__init__.py
pythonbook-1.0.dist-info/METADATA
pythonbook-1.0.dist-info/WHEEL
pythonbook-1.0.dist-info/top_level.txt
pythonbook-1.0.dist-info/RECORD
